SLML/SLML.py
SLML/__init__.py
StatLML-2.1.0.dist-info/LICENSE
StatLML-2.1.0.dist-info/METADATA
StatLML-2.1.0.dist-info/WHEEL
StatLML-2.1.0.dist-info/top_level.txt
StatLML-2.1.0.dist-info/RECORD
